{"t2": {"p": [{"23899": "Ashif Mulla"}, {"361952": "Rizwan Cheema"}, {"41440": "Mohammad Iqbal"}, {"23803": "Zubin Surkari"}, {"51738": "Sunil Dhaniram"}, {"365126": "Ramesh David"}, {"26826": "Balaji Rao"}, {"23860": "Sandeep Jyoti"}, {"355583": "Harvir Baidwan"}, {"52300": "Eion Katchay"}, {"372509": "Abzal Dean"}], "t": "0/10", "w": [{"ovr": "0.5", "how": "caught", "outby": "48835", "out": "23899"}, {"ovr": "2.3", "how": "leg before wicket", "outby": "48835", "out": "41440"}, {"ovr": "2.4", "how": "leg before wicket", "outby": "48835", "out": "23803"}, {"ovr": "10.1", "how": "leg before wicket", "outby": "268739", "out": "51738"}, {"ovr": "14.4", "how": "caught", "outby": "268739", "out": "365126"}, {"ovr": "15.2", "how": "caught", "outby": "49535", "out": "26826"}, {"ovr": "16.3", "how": "caught", "outby": "268739", "out": "361952"}, {"ovr": "16.6", "how": "leg before wicket", "outby": "268739", "out": "355583"}, {"ovr": "17.5", "how": "caught", "outby": "48487", "out": "52300"}, {"ovr": "19.6", "how": "caught", "outby": "48487", "out": "372509"}], "n": "Canada"}, "t1": {"p": [{"49209": "Sanath Jayasuriya"}, {"49633": "Jehan Mubarak"}, {"49289": "Mahela Jayawardene"}, {"49394": "Jeevantha Kulatunga"}, {"49363": "Thilina Kandamby"}, {"48472": "Tillakaratne Dilshan"}, {"50860": "Kaushalya Weeraratne"}, {"48487": "Dilhara Lokuhettige"}, {"49535": "Nuwan Kulasekara"}, {"48835": "Dilhara Fernando"}, {"268739": "Ajantha Mendis"}], "t": "0/7", "w": [{"ovr": "4.2", "how": "bowled", "outby": "52300", "out": "49209"}, {"ovr": "7.5", "how": "run out", "outby": "361952", "out": "49633"}, {"ovr": "10.3", "how": "leg before wicket", "outby": "26826", "out": "49289"}, {"ovr": "10.5", "how": "caught", "outby": "26826", "out": "49363"}, {"ovr": "14.2", "how": "caught", "outby": "26826", "out": "49394"}, {"ovr": "16.3", "how": "caught", "outby": "372509", "out": "50860"}, {"ovr": "18.5", "how": "stumped", "outby": "372509", "out": "48472"}], "n": "Sri Lanka"}}