{"runs": [{"o_u": "0.01", "ovr": "0.1", "bat": "219889", "r_t": "0", "bowl": "51782", "r": "0", "comm": "full, on the stumps, defended back to the bowler", "x": "148", "y": "195", "o_a": "0.1", "z": "6"}, {"o_u": "0.02", "ovr": "0.2", "bat": "219889", "r_t": "0", "bowl": "51782", "r": "0", "comm": "almost yorker length from Edwards, swinging a touch into Warner, who gets a thin inside edge on to hid pad, which saves him from an lbw decision", "x": "0", "y": "0", "o_a": "0.2", "z": "0"}, {"o_u": "0.03", "ovr": "0.3", "bat": "219889", "r_t": "0", "bowl": "51782", "r": "0", "comm": "length ball, on the stumps, played to cover", "x": "206", "y": "228", "o_a": "0.3", "z": "4"}, {"o_u": "0.04", "ovr": "0.4", "bat": "219889", "r_t": "1", "bowl": "51782", "r": "1", "comm": "pitched up and Warner swings his arms through it, smashing it on the half-volley <del>past extra-cover</del> ... no, wait, a superb diving stop keeps the damage to one", "x": "224", "y": "244", "o_a": "0.4", "z": "4"}, {"o_u": "0.05", "ovr": "0.5", "bat": "8180", "r_t": "0", "bowl": "51782", "r": "0", "comm": "pacy delivery, in the corridor, Watson swishes and misses", "x": "0", "y": "0", "o_a": "0.5", "z": "0"}, {"o_u": "0.06", "ovr": "0.6", "bat": "8180", "r_t": "0", "bowl": "51782", "r": "0", "comm": "gone, caught at slip! Watson was done for pace, Edwards whipping the ball through outside off and the Australia opener attempted a loose cut away from his body, only to edge to West Indies' captain", "x": "173", "y": "123", "o_a": "0.6", "z": "8"}, {"o_u": "1.01", "ovr": "1.1", "bat": "219889", "r_t": "0", "bowl": "230558", "r": "0", "comm": "tossed up outside off, played out towards cover", "x": "229", "y": "188", "o_a": "1.1", "z": "3"}, {"o_u": "1.02", "ovr": "1.2", "bat": "219889", "r_t": "0", "bowl": "230558", "r": "0", "comm": "on the stumps, defended coming forward", "x": "199", "y": "183", "o_a": "1.2", "z": "3"}, {"o_u": "1.03", "ovr": "1.3", "bat": "219889", "r_t": "0", "bowl": "230558", "r": "0", "comm": "shorter delivery, on the legs and Warner pulls but finds the man at short backward square", "x": "118", "y": "155", "o_a": "1.3", "z": "7"}, {"o_u": "1.04", "ovr": "1.4", "bat": "219889", "r_t": "1", "bowl": "230558", "r": "1", "comm": "flighted, dipping outside off, driven past point, who makes the stop but can't hold on to the ball", "x": "244", "y": "175", "o_a": "1.4", "z": "3"}, {"o_u": "1.05", "ovr": "1.5", "bat": "4451", "r_t": "1", "bowl": "230558", "r": "1", "comm": "flatter, on the stumps, whipped to leg where a diving Fidel Edwards half fields", "x": "289", "y": "153", "o_a": "1.5", "z": "2"}, {"o_u": "1.06", "ovr": "1.6", "bat": "219889", "r_t": "0", "bowl": "230558", "r": "0", "comm": "length, blocked towards mid-off from in front of the stumps", "x": "211", "y": "188", "o_a": "1.6", "z": "3"}, {"o_u": "2.01", "ovr": "2.1", "bat": "4451", "r_t": "1", "bowl": "51782", "r": "1", "comm": "bouncer, Bailey hooks ... dropped him! It flew hard and flat to Johnson Charles at long leg, he positioned himself to take it but it popped out of his grasp as he went with fingers up. Oh, Johnson!", "x": "279", "y": "52", "o_a": "2.1", "z": "1"}, {"o_u": "2.02", "ovr": "2.2", "bat": "219889", "r_t": "4", "bowl": "51782", "r": "4", "comm": "pitched up across the left-hander, wide of off stump, and shovelled over the infield for the first boundary of the innings", "x": "298", "y": "311", "o_a": "2.2", "z": "4"}, {"o_u": "2.03", "ovr": "2.3", "bat": "219889", "r_t": "0", "bowl": "51782", "r": "0", "comm": "around the wicket, holds a line wide of off, Warner goes down on one knee to slog but gets nothing on it", "x": "0", "y": "0", "o_a": "2.3", "z": "0"}, {"o_u": "2.04", "ovr": "2.4", "bat": "219889", "r_t": "0", "bowl": "51782", "r": "0", "comm": "straight through him this time! Speared, fast and bouncy, Warner swings across the line and the ball whistles <i>just</i> past the stumps", "x": "0", "y": "0", "o_a": "2.4", "z": "0"}, {"o_u": "2.05", "ovr": "2.5", "bat": "219889", "r_t": "4", "bowl": "51782", "r": "4", "comm": "bouncer, leaping up towards the throat, Warner rocks on his heels and guides an uppercut over point to the square boundary. Have at you!", "x": "341", "y": "135", "o_a": "2.5", "z": "2"}, {"o_u": "2.06", "ovr": "2.6", "bat": "219889", "r_t": "0", "bowl": "51782", "r": "0", "comm": "length ball this time, on the stumps and driven to mid-on", "x": "105", "y": "193", "o_a": "2.6", "z": "6"}, {"o_u": "3.01", "ovr": "3.1", "bat": "4451", "r_t": "0", "bowl": "252940", "r": "0", "comm": "on the stumps, tucked short to cover", "x": "161", "y": "187", "o_a": "3.1", "z": "5"}, {"o_u": "3.02", "ovr": "3.2", "bat": "4451", "r_t": "6", "bowl": "252940", "r": "6", "comm": "tossed up, straight delivery, not much turn and Bailey launches the ball back over long-on, for a mighty maximum", "x": "316", "y": "320", "o_a": "3.2", "z": "4"}, {"o_u": "3.03", "ovr": "3.3", "bat": "4451", "r_t": "0", "bowl": "252940", "r": "0", "comm": "shorter, on the stumps, Bailey tries to pull again but can't get it away", "x": "213", "y": "182", "o_a": "3.3", "z": "3"}, {"o_u": "3.04", "ovr": "3.4", "bat": "4451", "r_t": "2", "bowl": "252940", "r": "2", "comm": "sweeps from in front of the stumps to deep backward square leg", "x": "334", "y": "143", "o_a": "3.4", "z": "2"}, {"o_u": "3.05", "ovr": "3.5", "bat": "4451", "r_t": "1", "bowl": "252940", "r": "1", "comm": "flat, outside off, dabbed to short third man, the batsmen change their mind after starting to run and Bailey where's the throw on the back of his thigh", "x": "272", "y": "147", "o_a": "3.5", "z": "2"}, {"o_u": "3.06", "ovr": "3.6", "bat": "219889", "r_t": "6", "bowl": "252940", "r": "6", "comm": "drops short on the leg side, Warner smashes the ball up and over the deep square leg boundary like a man throwing a brick down a mineshaft", "x": "3", "y": "111", "o_a": "3.6", "z": "7"}, {"o_u": "4.01", "ovr": "4.1", "bat": "4451", "r_t": "1", "bowl": "53115", "r": "1", "comm": "short and pulled to deep square leg", "x": "306", "y": "142", "o_a": "4.1", "z": "2"}, {"o_u": "4.02", "ovr": "4.2", "bat": "219889", "r_t": "4", "bowl": "53115", "r": "4", "comm": "back of a length on the off side to Warner and he punches a cut shot through the infield. Not a great start from Sammy", "x": "358", "y": "245", "o_a": "4.2", "z": "3"}, {"o_u": "4.03", "ovr": "4.3", "bat": "219889", "r_t": "1", "bowl": "53115", "r": "1", "comm": "Baugh up to the stumps, fuller length, crashed towards extra-cover on the drive where Pollard makes a diving stop", "x": "234", "y": "253", "o_a": "4.3", "z": "4"}, {"o_u": "4.04", "ovr": "4.4", "bat": "4451", "r_t": "4", "bowl": "53115", "r": "4", "comm": "short and wide again, slapped dismissively through point for another boundary", "x": "10", "y": "193", "o_a": "4.4", "z": "6"}, {"o_u": "4.05", "ovr": "4.5", "bat": "4451", "r_t": "0", "bowl": "53115", "r": "0", "comm": "length, tighter line outside off, Bailey goes back and guides the ball to short third man", "x": "151", "y": "131", "o_a": "4.5", "z": "8"}, {"o_u": "4.06", "ovr": "4.6", "bat": "4451", "r_t": "1", "bowl": "53115", "r": "1", "comm": "on the stumps, doesn't really get up off a length, pulled flat towards deep backward square", "x": "307", "y": "85", "o_a": "4.6", "z": "2"}, {"o_u": "5.01", "ovr": "5.1", "bat": "4451", "r_t": "4", "bowl": "230558", "r": "4", "comm": "length, down the leg side and not much turn, helped on its way to the boundary by Bailey", "x": "328", "y": "92", "o_a": "5.1", "z": "2"}, {"o_u": "5.02", "ovr": "5.2", "bat": "4451", "r_t": "0", "bowl": "230558", "r": "0", "comm": "outside off, steered to short third man", "x": "149", "y": "130", "o_a": "5.2", "z": "8"}, {"o_u": "5.03", "ovr": "5.3", "bat": "4451", "r_t": "0", "bowl": "230558", "r": "0", "comm": "full, outside off, worked into the leg side", "x": "214", "y": "192", "o_a": "5.3", "z": "3"}, {"o_u": "5.04", "ovr": "5.4", "bat": "4451", "r_t": "1", "bowl": "230558", "r": "1", "comm": "flighted on the stumps, dug out to mid-on", "x": "227", "y": "302", "o_a": "5.4", "z": "4"}, {"o_u": "5.05", "ovr": "5.5", "bat": "219889", "r_t": "6", "bowl": "230558", "r": "6", "comm": "flatter delivery, carrom ball I think, on the stumps, dispatched far back over the bowler's head for another six!", "x": "9", "y": "256", "o_a": "5.5", "z": "6"}, {"o_u": "5.06", "ovr": "5.6", "bat": "219889", "r_t": "4", "bowl": "230558", "r": "4", "comm": "width outside off and slashed hard through point", "x": "362", "y": "216", "o_a": "5.6", "z": "3"}, {"o_u": "6.01", "ovr": "6.1", "bat": "4451", "r_t": "1", "bowl": "51439", "r": "1", "comm": "back of a length outside off, seaming in a touch, pulled through midwicket", "x": "308", "y": "189", "o_a": "6.1", "z": "3"}, {"o_u": "6.02", "ovr": "6.2", "bat": "219889", "r_t": "0", "bowl": "51439", "r": "0", "comm": "takes the pace off it, nurdled away on the off side", "x": "212", "y": "230", "o_a": "6.2", "z": "4"}, {"o_u": "6.03", "ovr": "6.3", "bat": "219889", "r_t": "1", "bowl": "51439", "r": "1", "comm": "pitched up on the legs, clipped to deep backward square", "x": "54", "y": "143", "o_a": "6.3", "z": "7"}, {"o_u": "6.04", "ovr": "6.4", "bat": "4451", "r_t": "1", "bowl": "51439", "r": "1", "comm": "good length, not much room to work with it outside off, chopped down to third man", "x": "126", "y": "138", "o_a": "6.4", "z": "7"}, {"o_u": "6.05", "ovr": "6.5", "bat": "219889", "r_t": "2", "bowl": "51439", "r": "2", "comm": "drifts down the leg side, punched off the pads and deep square leg has to come round to field", "x": "65", "y": "95", "o_a": "6.5", "z": "7"}, {"o_u": "6.06", "ovr": "6.6", "bat": "219889", "r_t": "1", "bowl": "51439", "r": "1", "comm": "full length, on the stumps, whipped away on the full to deep midwicket", "x": "61", "y": "132", "o_a": "6.6", "z": "7"}, {"o_u": "7.01", "ovr": "7.1", "bat": "219889", "r_t": "4", "bowl": "52983", "r": "4", "comm": "pitched up, in the slot and Warner smacks it back over deep midwicket. Ouch", "x": "72", "y": "315", "o_a": "7.1", "z": "5"}, {"o_u": "7.02", "ovr": "7.2", "bat": "219889", "r_t": "1", "bowl": "52983", "r": "1", "comm": "flatter, across Warner, nudged to cover", "x": "275", "y": "234", "o_a": "7.2", "z": "3"}, {"o_u": "7.03", "ovr": "7.3", "bat": "4451", "r_t": "0", "bowl": "52983", "r": "0", "comm": "a breakthrough from Samuels, as Bailey top-edges a sweep and deep square leg takes the catch running in from the boundary! Australia's captain (yep, the right one, this time) is caught with his fingers in the cookie jar and the tourists are two down", "x": "337", "y": "225", "o_a": "7.3", "z": "3"}, {"o_u": "7.04", "ovr": "7.4", "bat": "219889", "r_t": "0", "bowl": "52983", "r": "0", "comm": "quicker ball, almost a medium pace yorker, beats the batsman outside off", "x": "0", "y": "0", "o_a": "7.4", "z": "0"}, {"o_u": "7.05", "ovr": "7.5", "bat": "219889", "r_t": "0", "bowl": "52983", "r": "0", "comm": "length, not much turned, chopped to point who makes the save", "x": "235", "y": "156", "o_a": "7.5", "z": "2"}, {"o_u": "7.06", "ovr": "7.6", "bat": "219889", "r_t": "1", "bowl": "52983", "r": "1", "comm": "angled across and this time Warner gets a run to point", "x": "237", "y": "147", "o_a": "7.6", "z": "2"}, {"o_u": "8.01", "ovr": "8.1", "bat": "219889", "r_t": "0", "bowl": "51439", "r": "0", "comm": "pitched up, just outside off, driven into the ground and taken at extra-cover. The crowd get excited for a moment, but it was a bump ball", "x": "229", "y": "199", "o_a": "8.1", "z": "3"}, {"o_u": "8.02", "ovr": "8.2", "bat": "219889", "r_t": "0", "bowl": "51439", "r": "0", "comm": "slightly back of a length, rolls the fingers over it, blocked back to the bowler", "x": "172", "y": "200", "o_a": "8.2", "z": "5"}, {"o_u": "8.03", "ovr": "8.3", "bat": "219889", "r_t": "2", "bowl": "51439", "r": "2", "comm": "tossed up, slower ball again, Warner waits and punches into the gap in front of deep midwicket and they steal two", "x": "67", "y": "209", "o_a": "8.3", "z": "6"}, {"o_u": "8.04", "ovr": "8.4", "bat": "219889", "r_t": "1", "bowl": "51439", "r": "1", "comm": "full, on the legs, glanced to short third man - he has a shy but misses as they scramble a single", "x": "152", "y": "125", "o_a": "8.4", "z": "8"}, {"o_u": "8.05", "ovr": "8.5", "bat": "5939", "r_t": "1", "bowl": "51439", "r": "1", "comm": "slightly full, on off stump, driven through cover - Hussey is off the mark first ball", "x": "337", "y": "174", "o_a": "8.5", "z": "3"}, {"o_u": "8.06", "ovr": "8.6", "bat": "219889", "r_t": "1", "bowl": "51439", "r": "1", "comm": "pitched up, driven out to the fielder on the cover boundary", "x": "231", "y": "195", "o_a": "8.6", "z": "3"}, {"o_u": "9.01", "ovr": "9.1", "bat": "219889", "r_t": "1", "bowl": "52983", "r": "1", "comm": "on the stumps, dribbled down the ground to long-off", "x": "52", "y": "198", "o_a": "9.1", "z": "6"}, {"o_u": "9.02", "ovr": "9.2", "bat": "5939", "r_t": "0", "bowl": "52983", "r": "0", "comm": "tossed up, deflected to short third man", "x": "128", "y": "191", "o_a": "9.2", "z": "6"}, {"o_u": "9.03", "ovr": "9.3", "bat": "5939", "r_t": "1", "bowl": "52983", "r": "1", "comm": "top-edged as Hussey plays across the line ... but it falls short of long-on as he comes in off the rope. Lucky, Hussey, lucky", "x": "142", "y": "293", "o_a": "9.3", "z": "5"}, {"o_u": "9.04", "ovr": "9.4", "bat": "219889", "r_t": "1", "bowl": "52983", "r": "1", "comm": "flatter, pushed through outside off, dabbed to short third man", "x": "252", "y": "131", "o_a": "9.4", "z": "2"}, {"o_u": "9.05", "ovr": "9.5", "bat": "5939", "r_t": "1", "bowl": "52983", "r": "1", "comm": "dropped short behind point and again they steal one", "x": "299", "y": "187", "o_a": "9.5", "z": "3"}, {"o_u": "9.06", "ovr": "9.6", "bat": "219889", "r_t": "1", "bowl": "52983", "r": "1", "comm": "slanted across, length ball, driven through the covers", "x": "259", "y": "188", "o_a": "9.6", "z": "3"}, {"o_u": "10.01", "ovr": "10.1", "bat": "219889", "r_t": "1", "bowl": "230559", "r": "1", "comm": "back of a length, outside the left-hander's leg stump, pulled away square", "x": "59", "y": "127", "o_a": "10.1", "z": "7"}, {"o_u": "10.02", "ovr": "10.2", "bat": "5939", "r_t": "2", "bowl": "230559", "r": "2", "comm": "on the body, clipped square on the leg side ... Pollard breaks the stumps at the non-striker's end when the throw comes in bit he didn't take it cleanly anway", "x": "89", "y": "199", "o_a": "10.2", "z": "6"}, {"o_u": "10.03", "ovr": "10.3", "bat": "5939", "r_t": "1", "bowl": "230559", "r": "1", "comm": "length ball, played fine on the leg side", "x": "58", "y": "122", "o_a": "10.3", "z": "7"}, {"o_u": "10.04", "ovr": "10.4", "bat": "219889", "r_t": "0", "bowl": "230559", "r": "0", "comm": "fuller, on off and driven, fielded by mid-off", "x": "215", "y": "194", "o_a": "10.4", "z": "3"}, {"o_u": "10.05", "ovr": "10.5", "bat": "219889", "r_t": "1", "bowl": "230559", "r": "1", "comm": "back of a length, on leg stump, nudged round the corner for one - that's a well-paced fifty for Warner", "x": "72", "y": "134", "o_a": "10.5", "z": "7"}, {"o_u": "10.06", "ovr": "10.6", "bat": "5939", "r_t": "1", "bowl": "230559", "r": "1", "comm": "full, on the stumps, punched through midwicket", "x": "42", "y": "220", "o_a": "10.6", "z": "6"}, {"o_u": "11.01", "ovr": "11.1", "bat": "5939", "r_t": "6", "bowl": "52983", "r": "6", "comm": "flat and straight, no need for Hussey to worry about the turn and he sweeps BIG over deep midwicket", "x": "12", "y": "273", "o_a": "11.1", "z": "6"}, {"o_u": "11.02", "ovr": "11.2", "bat": "5939", "r_t": "1", "bowl": "52983", "r": "1", "comm": "outside off, drilled to the cover sweeper", "x": "60", "y": "140", "o_a": "11.2", "z": "7"}, {"o_u": "11.03", "ovr": "11.3", "bat": "219889", "r_t": "0", "bowl": "52983", "r": "0", "comm": "tight line across the batsman, played to cover", "x": "226", "y": "150", "o_a": "11.3", "z": "2"}, {"o_u": "11.04", "ovr": "11.4", "bat": "219889", "r_t": "1", "bowl": "52983", "r": "1", "comm": "flighted, driven down the ground for one", "x": "58", "y": "238", "o_a": "11.4", "z": "6"}, {"o_u": "11.05", "ovr": "11.5", "bat": "5939", "r_t": "0", "bowl": "52983", "r": "0", "comm": "given some air, miscues with a heave to leg and chips back to the bowler! Samuels strikes again! The ball didn't do much but Hussey's bat turned in his hands and the ball flew off the bottom of the bat straight back to the bowler", "x": "176", "y": "201", "o_a": "11.5", "z": "5"}, {"o_u": "11.06", "ovr": "11.6", "bat": "5766", "r_t": "1", "bowl": "52983", "r": "1", "comm": "length outside off, played square through cover-point", "x": "97", "y": "204", "o_a": "11.6", "z": "6"}, {"o_u": "12.01", "ovr": "12.1", "bat": "5766", "r_t": "1", "bowl": "252940", "r": "1", "comm": "length, driven to long-off", "x": "301", "y": "242", "o_a": "12.1", "z": "3"}, {"o_u": "12.02", "ovr": "12.2", "bat": "219889", "r_t": "6", "bowl": "252940", "r": "6", "comm": "drops short and Warner bombastically hooks high over deep square leg. I think he's lost the ball ...", "x": "5", "y": "110", "o_a": "12.2", "z": "7"}, {"o_u": "12.03", "ovr": "12.3", "bat": "219889", "r_t": "1", "bowl": "252940", "r": "1", "comm": "direct hit from mid-on removes Warner! They went for a second, taking on the arm of Dwayne Bravo, who charged in from the rope, picked up the ball in one hand and threw down the stumps in one smooth movement. Game changing?", "x": "71", "y": "213", "o_a": "12.3", "z": "6"}, {"o_u": "12.04", "ovr": "12.4", "bat": "230193", "r_t": "0", "bowl": "252940", "r": "0", "comm": "defended in front of the stumps", "x": "226", "y": "175", "o_a": "12.4", "z": "3"}, {"o_u": "12.05", "ovr": "12.5", "bat": "230193", "r_t": "0", "bowl": "252940", "r": "0", "comm": "flatter delivery, nudged into the leg side", "x": "243", "y": "185", "o_a": "12.5", "z": "3"}, {"o_u": "12.06", "ovr": "12.6", "bat": "230193", "r_t": "0", "bowl": "252940", "r": "0", "comm": "played off the batsman's legs, Mathurin fields himself and also hits the stumps - but Wade was <i>just</i> back", "x": "133", "y": "200", "o_a": "12.6", "z": "6"}, {"o_u": "13.01", "ovr": "13.1", "bat": "5766", "r_t": "1", "bowl": "230558", "r": "1", "comm": "on the stumps, turning across, played towards square leg off the pads", "x": "243", "y": "130", "o_a": "13.1", "z": "2"}, {"o_u": "13.02", "ovr": "13.2", "bat": "230193", "r_t": "0", "bowl": "230558", "r": "0", "comm": "length, turning across, dabbed to point", "x": "216", "y": "175", "o_a": "13.2", "z": "3"}, {"o_u": "13.03", "ovr": "13.3", "bat": "230193", "r_t": "4", "bowl": "230558", "r": "4", "comm": "tossed up, no real turn and Wade swings away across his front pad to the backward square boundary", "x": "9", "y": "134", "o_a": "13.3", "z": "7"}, {"o_u": "13.04", "ovr": "13.4", "bat": "230193", "r_t": "0", "bowl": "230558", "r": "0", "comm": "turn and bounce off a length, beats the outside edge", "x": "0", "y": "0", "o_a": "13.4", "z": "0"}, {"o_u": "13.05", "ovr": "13.5", "bat": "230193", "r_t": "1", "bowl": "230558", "r": "1", "comm": "on the stumps, goes back and nudges behind point", "x": "327", "y": "204", "o_a": "13.5", "z": "3"}, {"o_u": "13.06", "ovr": "13.6", "bat": "5766", "r_t": "0", "bowl": "230558", "r": "0", "comm": "outside off, comes forward and knocks into the off side", "x": "140", "y": "151", "o_a": "13.6", "z": "7"}, {"o_u": "14.01", "ovr": "14.1", "bat": "230193", "r_t": "1", "bowl": "51782", "r": "1", "comm": "back of a length, on the legs, Wade hops back and glances square", "x": "92", "y": "118", "o_a": "14.1", "z": "7"}, {"o_u": "14.02", "ovr": "14.2", "bat": "5766", "r_t": "0", "bowl": "51782", "r": "0", "comm": "fast and straight, whipped from in front of the stumps to the man at midwicket", "x": "225", "y": "210", "o_a": "14.2", "z": "3"}, {"o_u": "14.03", "ovr": "14.3", "bat": "5766", "r_t": "1", "bowl": "51782", "r": "0", "comm": "well outside off and the batsman can't get anywhere near that", "x": "0", "y": "0", "o_a": "14.3", "z": "0"}, {"o_u": "14.04", "ovr": "14.3", "bat": "5766", "r_t": "1", "bowl": "51782", "r": "1", "comm": "back of a length, outside off, swings and bottom edges past the stumps to short fine leg", "x": "229", "y": "124", "o_a": "14.3", "z": "2"}, {"o_u": "14.05", "ovr": "14.4", "bat": "230193", "r_t": "1", "bowl": "51782", "r": "1", "comm": "angled across, driven through the covers off a good length", "x": "350", "y": "179", "o_a": "14.4", "z": "3"}, {"o_u": "14.06", "ovr": "14.5", "bat": "5766", "r_t": "1", "bowl": "51782", "r": "0", "comm": "full and wide - Edwards thinks it was inside the return crease; the umpire doesn't", "x": "0", "y": "0", "o_a": "14.5", "z": "0"}, {"o_u": "14.07", "ovr": "14.5", "bat": "5766", "r_t": "0", "bowl": "51782", "r": "0", "comm": "rolls his fingers over it, edged on to the crease, Edwards cleans up off his own bowling to prevent a run", "x": "174", "y": "182", "o_a": "14.5", "z": "5"}, {"o_u": "14.08", "ovr": "14.6", "bat": "5766", "r_t": "2", "bowl": "51782", "r": "2", "comm": "is that a drop? I think it is ... It was a full-pitched delivery, Hussey tried to dig it out, got the toe of the bat on it, but Baugh couldn't hold on and the ball scooted away for four", "x": "149", "y": "27", "o_a": "14.6", "z": "8"}, {"o_u": "15.01", "ovr": "15.1", "bat": "230193", "r_t": "6", "bowl": "230558", "r": "6", "comm": "tossed up on middle and Wade clears his front foot out of the way and thumps the ball back over long-on", "x": "31", "y": "330", "o_a": "15.1", "z": "5"}, {"o_u": "15.02", "ovr": "15.2", "bat": "230193", "r_t": "1", "bowl": "230558", "r": "1", "comm": "leg stump, flicked off the pads square of the wicket", "x": "30", "y": "152", "o_a": "15.2", "z": "7"}, {"o_u": "15.03", "ovr": "15.3", "bat": "5766", "r_t": "0", "bowl": "230558", "r": "0", "comm": "on the stumps, blocked back to the bowler", "x": "188", "y": "185", "o_a": "15.3", "z": "4"}, {"o_u": "15.04", "ovr": "15.4", "bat": "5766", "r_t": "1", "bowl": "230558", "r": "1", "comm": "played off the pads to short fine leg, good work from the fielder and then Narine ensure the bails are broken at the non-striker's end ... but Hussey's bat was just in", "x": "234", "y": "133", "o_a": "15.4", "z": "2"}, {"o_u": "15.05", "ovr": "15.5", "bat": "230193", "r_t": "2", "bowl": "230558", "r": "2", "comm": "flighted on the stumps, driven with a flashing blade to extra-cover, who can't quite make the stop", "x": "304", "y": "263", "o_a": "15.5", "z": "3"}, {"o_u": "15.06", "ovr": "15.6", "bat": "230193", "r_t": "0", "bowl": "230558", "r": "0", "comm": "on the stumps, chopped back down the wicket", "x": "217", "y": "191", "o_a": "15.6", "z": "3"}, {"o_u": "16.01", "ovr": "16.1", "bat": "5766", "r_t": "4", "bowl": "51439", "r": "4", "comm": "pitched up and his first ball is lofted over extra-cover and away to the rope for four! Not the start his captain wanted", "x": "45", "y": "291", "o_a": "16.1", "z": "6"}, {"o_u": "16.02", "ovr": "16.2", "bat": "5766", "r_t": "6", "bowl": "51439", "r": "6", "comm": "good length, on the stumps, Hussey comes forward and whips a brutal aerial drive over long-on - that was clinical hitting", "x": "254", "y": "352", "o_a": "16.2", "z": "4"}, {"o_u": "16.03", "ovr": "16.3", "bat": "5766", "r_t": "1", "bowl": "51439", "r": "1", "comm": "fuller length, on the stumps, driven to long-on", "x": "228", "y": "293", "o_a": "16.3", "z": "4"}, {"o_u": "16.04", "ovr": "16.4", "bat": "230193", "r_t": "0", "bowl": "51439", "r": "0", "comm": "full, on the stumps and a touch slower, Wade can't get his drive away", "x": "202", "y": "184", "o_a": "16.4", "z": "3"}, {"o_u": "16.05", "ovr": "16.5", "bat": "230193", "r_t": "0", "bowl": "51439", "r": "0", "comm": "rolls his fingers over it again, turning it into an offcutter - Wade swings and misses, with the ball swerving past off stump on its way through to the keeper", "x": "0", "y": "0", "o_a": "16.5", "z": "0"}, {"o_u": "16.06", "ovr": "16.6", "bat": "230193", "r_t": "1", "bowl": "51439", "r": "1", "comm": "length, again taking the pace off, clubbed down the ground", "x": "209", "y": "353", "o_a": "16.6", "z": "4"}, {"o_u": "17.01", "ovr": "17.1", "bat": "230193", "r_t": "0", "bowl": "52983", "r": "0", "comm": "full, flat and quick, beats Wade outside off stump", "x": "0", "y": "0", "o_a": "17.1", "z": "0"}, {"o_u": "17.02", "ovr": "17.2", "bat": "230193", "r_t": "0", "bowl": "52983", "r": "0", "comm": "pushed across the batsman, driven to cover", "x": "245", "y": "172", "o_a": "17.2", "z": "3"}, {"o_u": "17.03", "ovr": "17.3", "bat": "230193", "r_t": "0", "bowl": "52983", "r": "0", "comm": "flighted a bit more, turning across the batsman who misses with a big swing, Baugh removing the bails just in case", "x": "0", "y": "0", "o_a": "17.3", "z": "0"}, {"o_u": "17.04", "ovr": "17.4", "bat": "230193", "r_t": "0", "bowl": "52983", "r": "0", "comm": "caught and bowled! It was basically a full toss and Wade smacked it straight back at Samuels, who anticipated the catch and took it comfortably moving to his right. But hold on, they're checking whether was a no-ball on height ... No, it was close but he's been given out", "x": "183", "y": "194", "o_a": "17.4", "z": "4"}, {"o_u": "17.05", "ovr": "17.5", "bat": "4864", "r_t": "2", "bowl": "52983", "r": "2", "comm": "full, on the stumps, chipped down the ground wide of long-on and they take a couple", "x": "265", "y": "279", "o_a": "17.5", "z": "4"}, {"o_u": "17.06", "ovr": "17.6", "bat": "4864", "r_t": "1", "bowl": "52983", "r": "1", "comm": "length outside off, Christian plays a premeditated paddle shot to short fine leg", "x": "212", "y": "101", "o_a": "17.6", "z": "1"}, {"o_u": "18.01", "ovr": "18.1", "bat": "4864", "r_t": "0", "bowl": "51782", "r": "0", "comm": "full and wide, chipped straight to extra-cover! Christian was nowhere near the pitch and simply levered the ball to Sammy at head height", "x": "119", "y": "206", "o_a": "18.1", "z": "6"}, {"o_u": "18.02", "ovr": "18.2", "bat": "6278", "r_t": "0", "bowl": "51782", "r": "0", "comm": "two in two balls for Edwards! Full, fast and straight, drifting in to the batsman and off stump goes pinwheeling away! Lee saw nothing off that - and Edwards is now on a hat-trick ...", "x": "0", "y": "0", "o_a": "18.2", "z": "0"}, {"o_u": "18.03", "ovr": "18.3", "bat": "6903", "r_t": "0", "bowl": "51782", "r": "0", "comm": "length, quick and seaming back in, McKay prods tentatively but it's too good for him", "x": "0", "y": "0", "o_a": "18.3", "z": "0"}, {"o_u": "18.04", "ovr": "18.4", "bat": "6903", "r_t": "0", "bowl": "51782", "r": "0", "comm": "pitched up, steps back and makes another air shot", "x": "0", "y": "0", "o_a": "18.4", "z": "0"}, {"o_u": "18.05", "ovr": "18.5", "bat": "6903", "r_t": "6", "bowl": "51782", "r": "6", "comm": "slings down a full toss on leg stump and McKay batters it down the ground for six! He gave that some humpty", "x": "174", "y": "362", "o_a": "18.5", "z": "5"}, {"o_u": "18.06", "ovr": "18.6", "bat": "6903", "r_t": "0", "bowl": "51782", "r": "0", "comm": "superb reply, a yorker wide of off stump, McKay had backed away and missed with a swish of the bat", "x": "0", "y": "0", "o_a": "18.6", "z": "0"}, {"o_u": "19.01", "ovr": "19.1", "bat": "5766", "r_t": "1", "bowl": "51439", "r": "1", "comm": "full, swinging towards leg stump, shovelled to deep backward square and they scamper through for one", "x": "285", "y": "248", "o_a": "19.1", "z": "3"}, {"o_u": "19.02", "ovr": "19.2", "bat": "6903", "r_t": "0", "bowl": "51439", "r": "0", "comm": "slight change in pace, angled in from wide of the crease, McKay misses with a swipe as the ball sails past leg stump ... Baugh then hits the wicket but the batsman had grounded his bat", "x": "0", "y": "0", "o_a": "19.2", "z": "0"}, {"o_u": "19.03", "ovr": "19.3", "bat": "6903", "r_t": "1", "bowl": "51439", "r": "1", "comm": "length, on the stumps, dumped in front of midwicket for a single", "x": "295", "y": "128", "o_a": "19.3", "z": "2"}, {"o_u": "19.04", "ovr": "19.4", "bat": "5766", "r_t": "0", "bowl": "51439", "r": "0", "comm": "gone, what a catch from Pollard! Hussey fastened on to a full ball on the stumps and thumped it out towards deep midwicket, where Pollard, running round from long-on dived full length to grasp the ball in his bucket-like hands", "x": "292", "y": "265", "o_a": "19.4", "z": "3"}, {"o_u": "19.05", "ovr": "19.5", "bat": "6903", "r_t": "0", "bowl": "51439", "r": "0", "comm": "slower ball on off, bowled him! Bravo is aeroplaning around the outfield after taking West Indies to the brink of victory. The ball was too good for McKay, who tried to hit it out of the ground but lost his off stump", "x": "0", "y": "0", "o_a": "19.5", "z": "0"}, {"o_u": "19.06", "ovr": "19.6", "bat": "5017", "r_t": "2", "bowl": "51439", "r": "2", "comm": "length ball, on the stumps, hooked out towards wide long-on, they come back for a couple but it's nowhere near enough - West Indies have won by 14 runs!", "x": "74", "y": "281", "o_a": "19.6", "z": "5"}]}